.DS_Store
.gitignore
LICENSE.txt
MANIFEST.in
README.md
cleditor.png
setup.py
.git/COMMIT_EDITMSG
.git/FETCH_HEAD
.git/HEAD
.git/ORIG_HEAD
.git/config
.git/description
.git/index
.git/packed-refs
.git/hooks/applypatch-msg.sample
.git/hooks/commit-msg.sample
.git/hooks/post-commit.sample
.git/hooks/post-receive.sample
.git/hooks/post-update.sample
.git/hooks/pre-applypatch.sample
.git/hooks/pre-commit.sample
.git/hooks/pre-rebase.sample
.git/hooks/prepare-commit-msg.sample
.git/hooks/update.sample
.git/info/exclude
.git/logs/HEAD
.git/logs/refs/heads/master
.git/logs/refs/remotes/origin/master
.git/objects/01/32a764db0c975d3a85ebf8edd99e1d84659b44
.git/objects/02/69a9f692f500b5f8fc35fecb3a911fb81ae245
.git/objects/04/e4f6d7d882a428e4b411e2c5624136fd172c89
.git/objects/0a/6aef8c92e56d5e4c3e00407b47fabe1ce8b553
.git/objects/0b/9a45736628c3189a381360380aca7baac2b53a
.git/objects/0b/d5e85321a91b5e092011d8209d779ec79d911e
.git/objects/0c/c508a0963dede79d5148613f4819d51633403b
.git/objects/0d/20b6487c61e7d1bde93acf4a14b7a89083a16d
.git/objects/0e/86ca94880534ddf2103c002f8f38c9c39f9a42
.git/objects/13/24dda7d9e18868a20c7b1130b0bbb4f10d3ec3
.git/objects/16/828c305abac8f01a763af56576c4cfa0d392ec
.git/objects/18/018e94e78104f6df13a5b84281bb2998cf0002
.git/objects/18/d752d750ca9ebb996bcc6da89f8164908d8656
.git/objects/18/d7a3d57e07c9d8d16904862f0823c23da8a72f
.git/objects/1c/1571cc8c0bfc8215fff39a63e2d47082c3ca67
.git/objects/1c/bd99329e78121fe280ba51688c28b96b1a173b
.git/objects/1e/e4bcb4dba53d3f8e0d0f7a22e57619d05b56f9
.git/objects/21/909313c79788adfc5cbc3fbb8f06c901743725
.git/objects/21/94d9db22212309af66af6ca2c9e309b53fe45e
.git/objects/22/1b89ab265922d99e07102b3eedc4d343ec7100
.git/objects/22/37422d118efe79d6b045ef959838b438050518
.git/objects/22/5ecf10f715ec50fb146afcc81440366ab09b6b
.git/objects/24/0ec027131714d923336afcfd11c4adc7f5ed4e
.git/objects/26/b156e09e9a2e3caf88ac074116a217606e6efc
.git/objects/28/c62361aaea87480abfb4ee7fb398df01fb703a
django_cleditor.egg-info/PKG-INFO
django_cleditor.egg-info/SOURCES.txt
django_cleditor.egg-info/dependency_links.txt
django_cleditor.egg-info/top_level.txt