Metadata-Version: 1.0
Name: django-cleditor
Version: 0.2.1
Summary: A django form widget for CLEditor (a super clean, MIT licensed WYSIWYG HTML editor) that handles uploading
Home-page: https://github.com/yuchant/django-cleditor
Author: Yuji Tomita
Author-email: yuji@yujitomita.com
License: UNKNOWN
Platform: UNKNOWN
Classifier: Environment :: Web Environment
Classifier: Intended Audience :: Developers
Classifier: Operating System :: OS Independent
Classifier: Programming Language :: Python
Classifier: Framework :: Django
